py_hamt/__init__.py
py_hamt/encryption_hamt_store.py
py_hamt/hamt.py
py_hamt/hamt_to_sharded_converter.py
py_hamt/sharded_zarr_store.py
py_hamt/store_httpx.py
py_hamt/zarr_hamt_store.py
py_hamt/reference/flat_zarr_store.py
py_hamt-3.3.0.dist-info/METADATA
py_hamt-3.3.0.dist-info/WHEEL
py_hamt-3.3.0.dist-info/licenses/LICENSE
py_hamt-3.3.0.dist-info/RECORD
