Metadata-Version: 2.4
Name: py-hamt
Version: 3.3.0
Summary: HAMT implementation for a content-addressed storage system.
License-File: LICENSE
Requires-Python: >=3.12
Requires-Dist: dag-cbor>=0.3.3
Requires-Dist: httpx[http2]>=0.28.1
Requires-Dist: msgspec>=0.18.6
Requires-Dist: multiformats[full]>=0.3.1.post4
Requires-Dist: pycryptodome>=3.21.0
Requires-Dist: zarr==3.0.9
